{"stat":"ok","pagination":{"offset":0,"limit":50,"total":13},"monitors":[{"id":801799160,"friendly_name":"2ГИС","url":"https://2gis.ru","type":1,"sub_type":"","keyword_type":0,"keyword_case_type":0,"keyword_value":"","port":"","interval":300,"timeout":30,"status":2,"create_datetime":1763232224,"logs":[],"userId":3161943,"custom_uptime_ratio":"100.000","custom_down_durations":"0","response_times":[{"datetime":1767138780,"value":1464},{"datetime":1767136620,"value":786},{"datetime":1767133200,"value":1410},{"datetime":1767130800,"value":1084},{"datetime":1767128100,"value":1166},{"datetime":1767125700,"value":925},{"datetime":1767123300,"value":1618},{"datetime":1767120900,"value":1000},{"datetime":1767118500,"value":1388},{"datetime":1767116100,"value":1401},{"datetime":1767113700,"value":1435},{"datetime":1767111300,"value":1165},{"datetime":1767108900,"value":1144},{"datetime":1767106500,"value":1111},{"datetime":1767104100,"value":2742},{"datetime":1767101700,"value":1352},{"datetime":1767099300,"value":1105},{"datetime":1767096900,"value":1065},{"datetime":1767094500,"value":1506},{"datetime":1767092100,"value":1091},{"datetime":1767089400,"value":1520},{"datetime":1767087000,"value":1042},{"datetime":1767084600,"value":1057},{"datetime":1767082200,"value":865},{"datetime":1767079800,"value":763},{"datetime":1767077400,"value":839},{"datetime":1767075000,"value":832},{"datetime":1767072600,"value":917},{"datetime":1767070200,"value":809},{"datetime":1767067800,"value":817},{"datetime":1767065400,"value":825},{"datetime":1767063000,"value":984},{"datetime":1767060600,"value":1051},{"datetime":1767058200,"value":748},{"datetime":1767055800,"value":788}],"average_response_time":"1119.429","responsetime_length":275},{"id":801799162,"friendly_name":"Google","url":"https://google.com","type":1,"sub_type":"","keyword_type":0,"keyword_case_type":0,"keyword_value":"","port":"","interval":300,"timeout":30,"status":2,"create_datetime":1763232236,"logs":[],"userId":3161943,"custom_uptime_ratio":"100.000","custom_down_durations":"0","response_times":[{"datetime":1767138900,"value":141},{"datetime":1767136500,"value":135},{"datetime":1767133200,"value":127},{"datetime":1767130800,"value":101},{"datetime":1767128400,"value":111},{"datetime":1767126000,"value":107},{"datetime":1767123600,"value":72},{"datetime":1767121200,"value":163},{"datetime":1767118800,"value":313},{"datetime":1767116400,"value":130},{"datetime":1767114000,"value":118},{"datetime":1767111600,"value":124},{"datetime":1767109200,"value":94},{"datetime":1767106800,"value":141},{"datetime":1767104400,"value":112},{"datetime":1767102000,"value":139},{"datetime":1767099600,"value":70},{"datetime":1767097200,"value":109},{"datetime":1767094800,"value":128},{"datetime":1767092400,"value":106},{"datetime":1767090000,"value":105},{"datetime":1767087600,"value":135},{"datetime":1767085200,"value":111},{"datetime":1767082800,"value":105},{"datetime":1767080400,"value":125},{"datetime":1767078000,"value":84},{"datetime":1767075600,"value":116},{"datetime":1767073200,"value":120},{"datetime":1767070800,"value":146},{"datetime":1767068400,"value":120},{"datetime":1767066000,"value":157},{"datetime":1767063600,"value":130},{"datetime":1767061200,"value":75},{"datetime":1767058500,"value":113},{"datetime":1767056100,"value":99}],"average_response_time":"121.159","responsetime_length":277},{"id":801799163,"friendly_name":"HeadHunter","url":"https://hh.ru","type":1,"sub_type":"","keyword_type":0,"keyword_case_type":0,"keyword_value":"","port":"","interval":300,"timeout":30,"status":2,"create_datetime":1763232245,"logs":[],"userId":3161943,"custom_uptime_ratio":"100.000","custom_down_durations":"0","response_times":[{"datetime":1767138840,"value":640},{"datetime":1767136380,"value":575},{"datetime":1767133200,"value":636},{"datetime":1767130800,"value":580},{"datetime":1767128400,"value":620},{"datetime":1767126000,"value":592},{"datetime":1767123600,"value":816},{"datetime":1767121200,"value":629},{"datetime":1767118800,"value":593},{"datetime":1767116400,"value":552},{"datetime":1767114000,"value":547},{"datetime":1767111600,"value":587},{"datetime":1767109200,"value":1175},{"datetime":1767106800,"value":577},{"datetime":1767104400,"value":567},{"datetime":1767102000,"value":1097},{"datetime":1767099600,"value":558},{"datetime":1767097200,"value":1002},{"datetime":1767094800,"value":941},{"datetime":1767092400,"value":961},{"datetime":1767090000,"value":642},{"datetime":1767087600,"value":593},{"datetime":1767085200,"value":1163},{"datetime":1767082800,"value":869},{"datetime":1767080400,"value":598},{"datetime":1767078000,"value":836},{"datetime":1767075600,"value":618},{"datetime":1767073200,"value":611},{"datetime":1767070800,"value":613},{"datetime":1767068400,"value":1159},{"datetime":1767066000,"value":1084},{"datetime":1767063600,"value":1296},{"datetime":1767061200,"value":840},{"datetime":1767058800,"value":539},{"datetime":1767056400,"value":644}],"average_response_time":"747.790","responsetime_length":276},{"id":801799165,"friendly_name":"Ivi","url":"https://ivi.ru","type":1,"sub_type":"","keyword_type":0,"keyword_case_type":0,"keyword_value":"","port":"","interval":300,"timeout":30,"status":2,"create_datetime":1763232256,"logs":[],"userId":3161943,"custom_uptime_ratio":"100.000","custom_down_durations":"0","response_times":[{"datetime":1767138960,"value":1328},{"datetime":1767136560,"value":1750},{"datetime":1767132900,"value":1500},{"datetime":1767130500,"value":1266},{"datetime":1767128100,"value":1642},{"datetime":1767125700,"value":1314},{"datetime":1767123300,"value":1155},{"datetime":1767120600,"value":1441},{"datetime":1767118200,"value":1284},{"datetime":1767115800,"value":1225},{"datetime":1767113400,"value":1273},{"datetime":1767111000,"value":1110},{"datetime":1767108600,"value":1546},{"datetime":1767106200,"value":1378},{"datetime":1767103800,"value":1318},{"datetime":1767101400,"value":1527},{"datetime":1767099000,"value":1103},{"datetime":1767096600,"value":1083},{"datetime":1767094200,"value":1430},{"datetime":1767091800,"value":1737},{"datetime":1767089400,"value":1246},{"datetime":1767087000,"value":1722},{"datetime":1767084600,"value":1533},{"datetime":1767082200,"value":1155},{"datetime":1767079800,"value":1367},{"datetime":1767077400,"value":1346},{"datetime":1767075000,"value":1416},{"datetime":1767072600,"value":1311},{"datetime":1767070200,"value":1077},{"datetime":1767067800,"value":1891},{"datetime":1767065400,"value":1345},{"datetime":1767063000,"value":1789},{"datetime":1767060600,"value":1245},{"datetime":1767057900,"value":2050},{"datetime":1767055500,"value":1872}],"average_response_time":"1415.429","responsetime_length":275},{"id":801799167,"friendly_name":"Mail.ru","url":"https://mail.ru","type":1,"sub_type":"","keyword_type":0,"keyword_case_type":0,"keyword_value":"","port":"","interval":300,"timeout":30,"status":2,"create_datetime":1763232267,"logs":[],"userId":3161943,"custom_uptime_ratio":"100.000","custom_down_durations":"0","response_times":[{"datetime":1767138840,"value":1038},{"datetime":1767136680,"value":701},{"datetime":1767133200,"value":1012},{"datetime":1767130800,"value":1255},{"datetime":1767128400,"value":964},{"datetime":1767126000,"value":1279},{"datetime":1767123600,"value":853},{"datetime":1767121200,"value":1463},{"datetime":1767118800,"value":1067},{"datetime":1767116400,"value":839},{"datetime":1767114000,"value":1362},{"datetime":1767111600,"value":1090},{"datetime":1767109200,"value":912},{"datetime":1767106800,"value":690},{"datetime":1767104400,"value":993},{"datetime":1767101700,"value":1030},{"datetime":1767099300,"value":1019},{"datetime":1767096900,"value":905},{"datetime":1767094500,"value":880},{"datetime":1767092100,"value":835},{"datetime":1767089700,"value":937},{"datetime":1767087300,"value":982},{"datetime":1767084900,"value":854},{"datetime":1767082500,"value":1001},{"datetime":1767080100,"value":782},{"datetime":1767077700,"value":900},{"datetime":1767075300,"value":804},{"datetime":1767072900,"value":897},{"datetime":1767070500,"value":832},{"datetime":1767068100,"value":1424},{"datetime":1767065700,"value":863},{"datetime":1767063300,"value":966},{"datetime":1767060900,"value":910},{"datetime":1767058500,"value":847},{"datetime":1767056100,"value":927}],"average_response_time":"980.000","responsetime_length":275},{"id":801799168,"friendly_name":"RuTube","url":"https://rutube.ru","type":1,"sub_type":"","keyword_type":0,"keyword_case_type":0,"keyword_value":"","port":"","interval":300,"timeout":30,"status":2,"create_datetime":1763232276,"logs":[],"userId":3161943,"custom_uptime_ratio":"100.000","custom_down_durations":"0","response_times":[{"datetime":1767138840,"value":440},{"datetime":1767136440,"value":439},{"datetime":1767133200,"value":407},{"datetime":1767130800,"value":393},{"datetime":1767128400,"value":491},{"datetime":1767126000,"value":450},{"datetime":1767123600,"value":369},{"datetime":1767121200,"value":393},{"datetime":1767118800,"value":940},{"datetime":1767116400,"value":416},{"datetime":1767114000,"value":373},{"datetime":1767111600,"value":384},{"datetime":1767109200,"value":410},{"datetime":1767106800,"value":525},{"datetime":1767104400,"value":431},{"datetime":1767102000,"value":642},{"datetime":1767099600,"value":479},{"datetime":1767097200,"value":483},{"datetime":1767094800,"value":495},{"datetime":1767092400,"value":409},{"datetime":1767090000,"value":388},{"datetime":1767087600,"value":609},{"datetime":1767085200,"value":596},{"datetime":1767082800,"value":490},{"datetime":1767080400,"value":753},{"datetime":1767078000,"value":362},{"datetime":1767075600,"value":490},{"datetime":1767073200,"value":724},{"datetime":1767070800,"value":370},{"datetime":1767068400,"value":794},{"datetime":1767066000,"value":473},{"datetime":1767063600,"value":457},{"datetime":1767061200,"value":488},{"datetime":1767058800,"value":552},{"datetime":1767056400,"value":461}],"average_response_time":"499.812","responsetime_length":276},{"id":801799170,"friendly_name":"Telegram","url":"https://telegram.org","type":1,"sub_type":"","keyword_type":0,"keyword_case_type":0,"keyword_value":"","port":"","interval":300,"timeout":30,"status":2,"create_datetime":1763232292,"logs":[],"userId":3161943,"custom_uptime_ratio":"100.000","custom_down_durations":"0","response_times":[{"datetime":1767138780,"value":287},{"datetime":1767136620,"value":268},{"datetime":1767133200,"value":265},{"datetime":1767130800,"value":268},{"datetime":1767128100,"value":271},{"datetime":1767125700,"value":266},{"datetime":1767123300,"value":292},{"datetime":1767120900,"value":276},{"datetime":1767118500,"value":273},{"datetime":1767116100,"value":281},{"datetime":1767113700,"value":276},{"datetime":1767111300,"value":775},{"datetime":1767108900,"value":274},{"datetime":1767106500,"value":271},{"datetime":1767104100,"value":291},{"datetime":1767101700,"value":270},{"datetime":1767099300,"value":266},{"datetime":1767096900,"value":266},{"datetime":1767094500,"value":268},{"datetime":1767092100,"value":270},{"datetime":1767089700,"value":272},{"datetime":1767087300,"value":300},{"datetime":1767084900,"value":278},{"datetime":1767082500,"value":280},{"datetime":1767080100,"value":268},{"datetime":1767077700,"value":267},{"datetime":1767075300,"value":260},{"datetime":1767072900,"value":263},{"datetime":1767070500,"value":277},{"datetime":1767068100,"value":288},{"datetime":1767065700,"value":279},{"datetime":1767063300,"value":260},{"datetime":1767060900,"value":281},{"datetime":1767058500,"value":277},{"datetime":1767056100,"value":269}],"average_response_time":"288.258","responsetime_length":275},{"id":801799172,"friendly_name":"Twitch","url":"https://twitch.tv","type":1,"sub_type":"","keyword_type":0,"keyword_case_type":0,"keyword_value":"","port":"","interval":300,"timeout":30,"status":2,"create_datetime":1763232301,"logs":[{"type":2,"datetime":1767138645,"duration":432,"reason":{"code":"200","detail":"OK"}},{"type":1,"datetime":1767138336,"duration":309,"reason":{"code":"405","detail":"Method Not Allowed"}},{"type":2,"datetime":1767136396,"duration":1940,"reason":{"code":"200","detail":"OK"}},{"type":1,"datetime":1767134864,"duration":1532,"reason":{"code":"405","detail":"Method Not Allowed"}},{"type":2,"datetime":1767129684,"duration":5180,"reason":{"code":"200","detail":"OK"}},{"type":1,"datetime":1767128762,"duration":922,"reason":{"code":"405","detail":"Method Not Allowed"}},{"type":2,"datetime":1767128071,"duration":691,"reason":{"code":"200","detail":"OK"}},{"type":1,"datetime":1767125622,"duration":2449,"reason":{"code":"405","detail":"Method Not Allowed"}},{"type":2,"datetime":1767124281,"duration":1341,"reason":{"code":"200","detail":"OK"}},{"type":1,"datetime":1767123666,"duration":615,"reason":{"code":"405","detail":"Method Not Allowed"}},{"type":2,"datetime":1767122976,"duration":690,"reason":{"code":"200","detail":"OK"}},{"type":1,"datetime":1767121753,"duration":1223,"reason":{"code":"405","detail":"Method Not Allowed"}},{"type":2,"datetime":1767121058,"duration":695,"reason":{"code":"200","detail":"OK"}},{"type":1,"datetime":1767120750,"duration":308,"reason":{"code":"405","detail":"Method Not Allowed"}},{"type":2,"datetime":1767116237,"duration":4513,"reason":{"code":"200","detail":"OK"}},{"type":1,"datetime":1767115932,"duration":305,"reason":{"code":"405","detail":"Method Not Allowed"}},{"type":2,"datetime":1767114558,"duration":1374,"reason":{"code":"200","detail":"OK"}},{"type":1,"datetime":1767114254,"duration":304,"reason":{"code":"405","detail":"Method Not Allowed"}},{"type":2,"datetime":1767112259,"duration":1995,"reason":{"code":"200","detail":"OK"}},{"type":1,"datetime":1767111648,"duration":611,"reason":{"code":"405","detail":"Method Not Allowed"}},{"type":2,"datetime":1767105165,"duration":6483,"reason":{"code":"200","detail":"OK"}},{"type":1,"datetime":1767104555,"duration":610,"reason":{"code":"405","detail":"Method Not Allowed"}},{"type":2,"datetime":1767101944,"duration":2611,"reason":{"code":"200","detail":"OK"}},{"type":1,"datetime":1767101028,"duration":916,"reason":{"code":"405","detail":"Method Not Allowed"}},{"type":2,"datetime":1767076759,"duration":24269,"reason":{"code":"200","detail":"OK"}},{"type":1,"datetime":1767075838,"duration":921,"reason":{"code":"405","detail":"Method Not Allowed"}},{"type":2,"datetime":1767070641,"duration":5197,"reason":{"code":"200","detail":"OK"}},{"type":1,"datetime":1767070017,"duration":624,"reason":{"code":"405","detail":"Method Not Allowed"}},{"type":2,"datetime":1767067496,"duration":2521,"reason":{"code":"200","detail":"OK"}},{"type":1,"datetime":1767067192,"duration":304,"reason":{"code":"405","detail":"Method Not Allowed"}},{"type":2,"datetime":1767063664,"duration":3528,"reason":{"code":"200","detail":"OK"}},{"type":1,"datetime":1767062442,"duration":1222,"reason":{"code":"405","detail":"Method Not Allowed"}},{"type":2,"datetime":1767062069,"duration":373,"reason":{"code":"200","detail":"OK"}},{"type":1,"datetime":1767060832,"duration":1237,"reason":{"code":"405","detail":"Method Not Allowed"}},{"type":2,"datetime":1767058399,"duration":2433,"reason":{"code":"200","detail":"OK"}},{"type":1,"datetime":1767057790,"duration":609,"reason":{"code":"405","detail":"Method Not Allowed"}},{"type":2,"datetime":1767057325,"duration":465,"reason":{"code":"200","detail":"OK"}},{"type":1,"datetime":1767057012,"duration":313,"reason":{"code":"405","detail":"Method Not Allowed"}},{"type":2,"datetime":1767049194,"duration":7818,"reason":{"code":"200","detail":"OK"}},{"type":1,"datetime":1767048273,"duration":921,"reason":{"code":"405","detail":"Method Not Allowed"}},{"type":98,"datetime":1765957275,"duration":0,"reason":{"code":98,"detail":"Monitor started"}},{"type":99,"datetime":1765957271,"duration":4,"reason":{"code":99,"detail":"Monitor paused"}}],"userId":3161943,"custom_uptime_ratio":"97.312","custom_down_durations":"16255","response_times":[{"datetime":1767138960,"value":75},{"datetime":1767136680,"value":103},{"datetime":1767133200,"value":58},{"datetime":1767130800,"value":82},{"datetime":1767128100,"value":81},{"datetime":1767125700,"value":51},{"datetime":1767123300,"value":32},{"datetime":1767120900,"value":38},{"datetime":1767118500,"value":66},{"datetime":1767116100,"value":77},{"datetime":1767113700,"value":50},{"datetime":1767111300,"value":99},{"datetime":1767108900,"value":62},{"datetime":1767106500,"value":60},{"datetime":1767104100,"value":84},{"datetime":1767101700,"value":52},{"datetime":1767099300,"value":50},{"datetime":1767096900,"value":23},{"datetime":1767094500,"value":42},{"datetime":1767092100,"value":84},{"datetime":1767089700,"value":54},{"datetime":1767087300,"value":49},{"datetime":1767084900,"value":76},{"datetime":1767082500,"value":64},{"datetime":1767080100,"value":74},{"datetime":1767077700,"value":54},{"datetime":1767075300,"value":64},{"datetime":1767072900,"value":61},{"datetime":1767070500,"value":70},{"datetime":1767068100,"value":58},{"datetime":1767065700,"value":44},{"datetime":1767063300,"value":34},{"datetime":1767060900,"value":58},{"datetime":1767058500,"value":62},{"datetime":1767056100,"value":61}],"average_response_time":"60.473","responsetime_length":279},{"id":801799173,"friendly_name":"Госуслуги","url":"https://gosuslugi.ru","type":1,"sub_type":"","keyword_type":0,"keyword_case_type":0,"keyword_value":"","port":"","interval":300,"timeout":30,"status":2,"create_datetime":1763232314,"logs":[],"userId":3161943,"custom_uptime_ratio":"100.000","custom_down_durations":"0","response_times":[{"datetime":1767139020,"value":374},{"datetime":1767136860,"value":429},{"datetime":1767133200,"value":422},{"datetime":1767130800,"value":387},{"datetime":1767128400,"value":412},{"datetime":1767126000,"value":400},{"datetime":1767123600,"value":557},{"datetime":1767121200,"value":554},{"datetime":1767118800,"value":487},{"datetime":1767116100,"value":419},{"datetime":1767113700,"value":492},{"datetime":1767111300,"value":521},{"datetime":1767108900,"value":476},{"datetime":1767106500,"value":343},{"datetime":1767104100,"value":452},{"datetime":1767101700,"value":460},{"datetime":1767099300,"value":445},{"datetime":1767096900,"value":391},{"datetime":1767094500,"value":572},{"datetime":1767092100,"value":433},{"datetime":1767089700,"value":448},{"datetime":1767087300,"value":384},{"datetime":1767084900,"value":398},{"datetime":1767082500,"value":417},{"datetime":1767080100,"value":412},{"datetime":1767077700,"value":430},{"datetime":1767075300,"value":393},{"datetime":1767072900,"value":407},{"datetime":1767070200,"value":395},{"datetime":1767067800,"value":405},{"datetime":1767065100,"value":512},{"datetime":1767062700,"value":371},{"datetime":1767060300,"value":436},{"datetime":1767057900,"value":424},{"datetime":1767055500,"value":412}],"average_response_time":"437.325","responsetime_length":268},{"id":801799180,"friendly_name":"КиноПоиск","url":"https://kinopoisk.ru","type":1,"sub_type":"","keyword_type":0,"keyword_case_type":0,"keyword_value":"","port":"","interval":300,"timeout":30,"status":2,"create_datetime":1763232380,"logs":[],"userId":3161943,"custom_uptime_ratio":"100.000","custom_down_durations":"0","response_times":[{"datetime":1767138780,"value":1271},{"datetime":1767136320,"value":2796},{"datetime":1767133200,"value":1306},{"datetime":1767130800,"value":1372},{"datetime":1767128100,"value":1260},{"datetime":1767125700,"value":1397},{"datetime":1767123300,"value":1817},{"datetime":1767120900,"value":1795},{"datetime":1767118500,"value":1611},{"datetime":1767115800,"value":1333},{"datetime":1767113400,"value":1598},{"datetime":1767111000,"value":1736},{"datetime":1767108600,"value":1759},{"datetime":1767106200,"value":1329},{"datetime":1767103800,"value":1760},{"datetime":1767101400,"value":1188},{"datetime":1767099000,"value":1516},{"datetime":1767096600,"value":1547},{"datetime":1767094200,"value":1504},{"datetime":1767091500,"value":1472},{"datetime":1767089100,"value":1386},{"datetime":1767086700,"value":1338},{"datetime":1767084300,"value":1504},{"datetime":1767081900,"value":1370},{"datetime":1767079500,"value":1444},{"datetime":1767077100,"value":1598},{"datetime":1767074700,"value":1617},{"datetime":1767072300,"value":1505},{"datetime":1767069900,"value":1526},{"datetime":1767067500,"value":1664},{"datetime":1767065100,"value":1323},{"datetime":1767062700,"value":1602},{"datetime":1767060300,"value":1531},{"datetime":1767057900,"value":1517},{"datetime":1767055500,"value":1482}],"average_response_time":"1516.529","responsetime_length":274},{"id":801799178,"friendly_name":"Пикабу","url":"https://pikabu.ru","type":1,"sub_type":"","keyword_type":0,"keyword_case_type":0,"keyword_value":"","port":"","interval":300,"timeout":30,"status":2,"create_datetime":1763232370,"logs":[],"userId":3161943,"custom_uptime_ratio":"100.000","custom_down_durations":"0","response_times":[{"datetime":1767138840,"value":377},{"datetime":1767136680,"value":401},{"datetime":1767133200,"value":396},{"datetime":1767130800,"value":399},{"datetime":1767128400,"value":485},{"datetime":1767126000,"value":416},{"datetime":1767123600,"value":400},{"datetime":1767121200,"value":479},{"datetime":1767118800,"value":415},{"datetime":1767116400,"value":443},{"datetime":1767114000,"value":458},{"datetime":1767111300,"value":444},{"datetime":1767108900,"value":417},{"datetime":1767106500,"value":457},{"datetime":1767104100,"value":460},{"datetime":1767101700,"value":443},{"datetime":1767099300,"value":723},{"datetime":1767096600,"value":447},{"datetime":1767094200,"value":438},{"datetime":1767091800,"value":442},{"datetime":1767089400,"value":434},{"datetime":1767087000,"value":424},{"datetime":1767084600,"value":415},{"datetime":1767082200,"value":425},{"datetime":1767079800,"value":425},{"datetime":1767077400,"value":440},{"datetime":1767075000,"value":406},{"datetime":1767072600,"value":402},{"datetime":1767070200,"value":412},{"datetime":1767067800,"value":412},{"datetime":1767065400,"value":386},{"datetime":1767063000,"value":396},{"datetime":1767060600,"value":399},{"datetime":1767058200,"value":420},{"datetime":1767055800,"value":445}],"average_response_time":"433.094","responsetime_length":276},{"id":801799174,"friendly_name":"СберМегаМаркет","url":"https://sbermegamarket.ru","type":1,"sub_type":"","keyword_type":0,"keyword_case_type":0,"keyword_value":"","port":"","interval":300,"timeout":30,"status":9,"create_datetime":1763232331,"logs":[{"type":1,"datetime":1767043713,"duration":0,"reason":{"code":"403","detail":"Forbidden"}}],"userId":3161943,"custom_uptime_ratio":"0.000","custom_down_durations":"604800","response_times":[{"datetime":1767138660,"value":545},{"datetime":1767135780,"value":444},{"datetime":1767132600,"value":567},{"datetime":1767130200,"value":564},{"datetime":1767127800,"value":573},{"datetime":1767125400,"value":576},{"datetime":1767123000,"value":613},{"datetime":1767120600,"value":552},{"datetime":1767118200,"value":688},{"datetime":1767115800,"value":596},{"datetime":1767113400,"value":555},{"datetime":1767111000,"value":467},{"datetime":1767108600,"value":512},{"datetime":1767106200,"value":503},{"datetime":1767103800,"value":634},{"datetime":1767101400,"value":539},{"datetime":1767099000,"value":545},{"datetime":1767096600,"value":524},{"datetime":1767094200,"value":503},{"datetime":1767091800,"value":572},{"datetime":1767089400,"value":581},{"datetime":1767087000,"value":532},{"datetime":1767084600,"value":643},{"datetime":1767082200,"value":542},{"datetime":1767079800,"value":555},{"datetime":1767077400,"value":479},{"datetime":1767075000,"value":491},{"datetime":1767072600,"value":526},{"datetime":1767070200,"value":613},{"datetime":1767067800,"value":530},{"datetime":1767065400,"value":498},{"datetime":1767063000,"value":516},{"datetime":1767060600,"value":591},{"datetime":1767058200,"value":529},{"datetime":1767055800,"value":603}],"average_response_time":"551.504","responsetime_length":266},{"id":801799175,"friendly_name":"Хитрая Лиса API","url":"https://slyfox.su","type":1,"sub_type":"","keyword_type":0,"keyword_case_type":0,"keyword_value":"","port":"","interval":300,"timeout":30,"status":2,"create_datetime":1763232343,"logs":[{"type":98,"datetime":1765957233,"duration":0,"reason":{"code":98,"detail":"Monitor started"}},{"type":99,"datetime":1765957228,"duration":5,"reason":{"code":99,"detail":"Monitor paused"}}],"userId":3161943,"custom_uptime_ratio":"100.000","custom_down_durations":"0","response_times":[{"datetime":1767139020,"value":429},{"datetime":1767136560,"value":373},{"datetime":1767133200,"value":514},{"datetime":1767130800,"value":312},{"datetime":1767128400,"value":392},{"datetime":1767126000,"value":342},{"datetime":1767123600,"value":218},{"datetime":1767121200,"value":345},{"datetime":1767118800,"value":345},{"datetime":1767116400,"value":326},{"datetime":1767114000,"value":451},{"datetime":1767111600,"value":310},{"datetime":1767109200,"value":414},{"datetime":1767106800,"value":353},{"datetime":1767104400,"value":219},{"datetime":1767102000,"value":256},{"datetime":1767099600,"value":287},{"datetime":1767097200,"value":386},{"datetime":1767094800,"value":406},{"datetime":1767092400,"value":387},{"datetime":1767090000,"value":320},{"datetime":1767087600,"value":425},{"datetime":1767085200,"value":330},{"datetime":1767082800,"value":394},{"datetime":1767080400,"value":459},{"datetime":1767078000,"value":301},{"datetime":1767075600,"value":434},{"datetime":1767073200,"value":263},{"datetime":1767070800,"value":418},{"datetime":1767068400,"value":432},{"datetime":1767066000,"value":458},{"datetime":1767063600,"value":292},{"datetime":1767061200,"value":401},{"datetime":1767058800,"value":426},{"datetime":1767056400,"value":298}],"average_response_time":"359.851","responsetime_length":276}]}