{"stat":"ok","pagination":{"offset":0,"limit":50,"total":13},"monitors":[{"id":801799160,"friendly_name":"2ГИС","url":"https://2gis.ru","type":1,"sub_type":"","keyword_type":0,"keyword_case_type":0,"keyword_value":"","port":"","interval":300,"timeout":30,"status":2,"create_datetime":1763232224,"logs":[],"userId":3161943,"custom_uptime_ratio":"100.000","custom_down_durations":"0","response_times":[{"datetime":1767480540,"value":1174},{"datetime":1767478380,"value":826},{"datetime":1767475200,"value":1120},{"datetime":1767472800,"value":1317},{"datetime":1767470400,"value":1074},{"datetime":1767468000,"value":1326},{"datetime":1767465600,"value":1584},{"datetime":1767463200,"value":1416},{"datetime":1767460800,"value":1312},{"datetime":1767458400,"value":1662},{"datetime":1767456000,"value":1374},{"datetime":1767453600,"value":1269},{"datetime":1767451200,"value":1053},{"datetime":1767448800,"value":1253},{"datetime":1767446400,"value":1045},{"datetime":1767444000,"value":948},{"datetime":1767441600,"value":928},{"datetime":1767439200,"value":846},{"datetime":1767436800,"value":1132},{"datetime":1767434400,"value":1454},{"datetime":1767432000,"value":1027},{"datetime":1767429600,"value":1017},{"datetime":1767427200,"value":1071},{"datetime":1767424800,"value":1061},{"datetime":1767422400,"value":1079},{"datetime":1767420000,"value":976},{"datetime":1767417600,"value":1159},{"datetime":1767415200,"value":1176},{"datetime":1767412800,"value":1088},{"datetime":1767410100,"value":1048},{"datetime":1767407700,"value":1017},{"datetime":1767405300,"value":1114},{"datetime":1767402900,"value":1237},{"datetime":1767400500,"value":894},{"datetime":1767398100,"value":1048},{"datetime":1767395700,"value":983},{"datetime":1767369600,"value":1666},{"datetime":1767364200,"value":1030},{"datetime":1767358800,"value":1139},{"datetime":1767353400,"value":1165},{"datetime":1767348000,"value":1166}],"average_response_time":"1158.471","responsetime_length":295},{"id":801799162,"friendly_name":"Google","url":"https://google.com","type":1,"sub_type":"","keyword_type":0,"keyword_case_type":0,"keyword_value":"","port":"","interval":300,"timeout":30,"status":2,"create_datetime":1763232236,"logs":[],"userId":3161943,"custom_uptime_ratio":"100.000","custom_down_durations":"0","response_times":[{"datetime":1767480540,"value":171},{"datetime":1767478380,"value":120},{"datetime":1767475200,"value":124},{"datetime":1767472800,"value":122},{"datetime":1767470400,"value":101},{"datetime":1767468000,"value":110},{"datetime":1767465300,"value":105},{"datetime":1767462900,"value":113},{"datetime":1767460500,"value":112},{"datetime":1767458100,"value":75},{"datetime":1767455700,"value":110},{"datetime":1767453300,"value":121},{"datetime":1767450900,"value":112},{"datetime":1767448500,"value":103},{"datetime":1767446100,"value":102},{"datetime":1767443700,"value":79},{"datetime":1767441300,"value":92},{"datetime":1767438900,"value":130},{"datetime":1767436500,"value":62},{"datetime":1767434100,"value":102},{"datetime":1767431700,"value":138},{"datetime":1767429300,"value":130},{"datetime":1767426900,"value":117},{"datetime":1767424500,"value":129},{"datetime":1767422100,"value":94},{"datetime":1767419700,"value":77},{"datetime":1767417300,"value":102},{"datetime":1767414600,"value":125},{"datetime":1767412200,"value":111},{"datetime":1767409800,"value":119},{"datetime":1767407400,"value":137},{"datetime":1767405000,"value":184},{"datetime":1767402600,"value":115},{"datetime":1767400200,"value":94},{"datetime":1767397800,"value":149}],"average_response_time":"114.000","responsetime_length":278},{"id":801799163,"friendly_name":"HeadHunter","url":"https://hh.ru","type":1,"sub_type":"","keyword_type":0,"keyword_case_type":0,"keyword_value":"","port":"","interval":300,"timeout":30,"status":2,"create_datetime":1763232245,"logs":[],"userId":3161943,"custom_uptime_ratio":"100.000","custom_down_durations":"0","response_times":[{"datetime":1767480600,"value":667},{"datetime":1767478440,"value":925},{"datetime":1767475200,"value":589},{"datetime":1767472800,"value":609},{"datetime":1767470400,"value":708},{"datetime":1767468000,"value":795},{"datetime":1767465600,"value":665},{"datetime":1767463200,"value":644},{"datetime":1767460800,"value":686},{"datetime":1767458400,"value":1101},{"datetime":1767456000,"value":678},{"datetime":1767453600,"value":621},{"datetime":1767451200,"value":1084},{"datetime":1767448800,"value":543},{"datetime":1767446400,"value":605},{"datetime":1767444000,"value":658},{"datetime":1767441600,"value":611},{"datetime":1767439200,"value":561},{"datetime":1767436800,"value":642},{"datetime":1767434400,"value":719},{"datetime":1767432000,"value":1172},{"datetime":1767429600,"value":613},{"datetime":1767427200,"value":608},{"datetime":1767424800,"value":623},{"datetime":1767422400,"value":802},{"datetime":1767420000,"value":730},{"datetime":1767417600,"value":1174},{"datetime":1767415200,"value":600},{"datetime":1767412800,"value":920},{"datetime":1767410400,"value":615},{"datetime":1767408000,"value":857},{"datetime":1767405600,"value":737},{"datetime":1767403200,"value":940},{"datetime":1767400800,"value":635},{"datetime":1767398400,"value":612}],"average_response_time":"733.158","responsetime_length":278},{"id":801799165,"friendly_name":"Ivi","url":"https://ivi.ru","type":1,"sub_type":"","keyword_type":0,"keyword_case_type":0,"keyword_value":"","port":"","interval":300,"timeout":30,"status":2,"create_datetime":1763232256,"logs":[],"userId":3161943,"custom_uptime_ratio":"100.000","custom_down_durations":"0","response_times":[{"datetime":1767480540,"value":1767},{"datetime":1767478380,"value":1586},{"datetime":1767475200,"value":1210},{"datetime":1767472800,"value":1332},{"datetime":1767470400,"value":1605},{"datetime":1767468000,"value":1134},{"datetime":1767465600,"value":1921},{"datetime":1767463200,"value":1408},{"datetime":1767460800,"value":1072},{"datetime":1767458400,"value":1410},{"datetime":1767456000,"value":1036},{"datetime":1767453600,"value":1221},{"datetime":1767451200,"value":1077},{"datetime":1767448800,"value":1610},{"datetime":1767446400,"value":1200},{"datetime":1767444000,"value":1608},{"datetime":1767441600,"value":1150},{"datetime":1767439200,"value":977},{"datetime":1767436800,"value":1545},{"datetime":1767434400,"value":1240},{"datetime":1767432000,"value":1181},{"datetime":1767429600,"value":1213},{"datetime":1767427200,"value":1482},{"datetime":1767424800,"value":1317},{"datetime":1767422400,"value":1199},{"datetime":1767420000,"value":1651},{"datetime":1767417600,"value":1763},{"datetime":1767415200,"value":1457},{"datetime":1767412800,"value":1127},{"datetime":1767410400,"value":1595},{"datetime":1767408000,"value":1478},{"datetime":1767405600,"value":1062},{"datetime":1767403200,"value":1927},{"datetime":1767400800,"value":1684},{"datetime":1767398400,"value":1435}],"average_response_time":"1391.166","responsetime_length":277},{"id":801799167,"friendly_name":"Mail.ru","url":"https://mail.ru","type":1,"sub_type":"","keyword_type":0,"keyword_case_type":0,"keyword_value":"","port":"","interval":300,"timeout":30,"status":2,"create_datetime":1763232267,"logs":[],"userId":3161943,"custom_uptime_ratio":"100.000","custom_down_durations":"0","response_times":[{"datetime":1767480540,"value":875},{"datetime":1767478080,"value":546},{"datetime":1767475200,"value":1162},{"datetime":1767472800,"value":1108},{"datetime":1767470400,"value":1121},{"datetime":1767468000,"value":908},{"datetime":1767465600,"value":953},{"datetime":1767463200,"value":1008},{"datetime":1767460800,"value":956},{"datetime":1767458400,"value":902},{"datetime":1767456000,"value":971},{"datetime":1767453600,"value":908},{"datetime":1767451200,"value":837},{"datetime":1767448800,"value":986},{"datetime":1767446400,"value":1415},{"datetime":1767444000,"value":891},{"datetime":1767441600,"value":978},{"datetime":1767439200,"value":978},{"datetime":1767436500,"value":951},{"datetime":1767434100,"value":914},{"datetime":1767431700,"value":889},{"datetime":1767429300,"value":1000},{"datetime":1767426900,"value":1019},{"datetime":1767424500,"value":757},{"datetime":1767422100,"value":957},{"datetime":1767419700,"value":841},{"datetime":1767417300,"value":842},{"datetime":1767414900,"value":879},{"datetime":1767412500,"value":1006},{"datetime":1767410100,"value":870},{"datetime":1767407700,"value":693},{"datetime":1767405300,"value":927},{"datetime":1767402900,"value":867},{"datetime":1767400500,"value":664},{"datetime":1767398100,"value":1013}],"average_response_time":"937.579","responsetime_length":278},{"id":801799168,"friendly_name":"RuTube","url":"https://rutube.ru","type":1,"sub_type":"","keyword_type":0,"keyword_case_type":0,"keyword_value":"","port":"","interval":300,"timeout":30,"status":2,"create_datetime":1763232276,"logs":[],"userId":3161943,"custom_uptime_ratio":"100.000","custom_down_durations":"0","response_times":[{"datetime":1767480660,"value":512},{"datetime":1767478200,"value":401},{"datetime":1767474900,"value":416},{"datetime":1767472500,"value":446},{"datetime":1767470100,"value":636},{"datetime":1767467700,"value":413},{"datetime":1767465300,"value":478},{"datetime":1767462900,"value":463},{"datetime":1767460500,"value":387},{"datetime":1767458100,"value":645},{"datetime":1767455700,"value":457},{"datetime":1767453300,"value":503},{"datetime":1767450900,"value":374},{"datetime":1767448500,"value":712},{"datetime":1767446100,"value":476},{"datetime":1767443400,"value":396},{"datetime":1767441000,"value":480},{"datetime":1767438600,"value":430},{"datetime":1767436200,"value":378},{"datetime":1767433800,"value":451},{"datetime":1767431400,"value":385},{"datetime":1767429000,"value":379},{"datetime":1767426600,"value":423},{"datetime":1767424200,"value":760},{"datetime":1767421800,"value":646},{"datetime":1767419400,"value":555},{"datetime":1767417000,"value":556},{"datetime":1767414600,"value":402},{"datetime":1767411900,"value":348},{"datetime":1767409500,"value":600},{"datetime":1767407100,"value":531},{"datetime":1767404700,"value":424},{"datetime":1767402300,"value":426},{"datetime":1767399900,"value":429},{"datetime":1767397500,"value":458},{"datetime":1767394800,"value":601},{"datetime":1767369600,"value":453},{"datetime":1767364200,"value":482},{"datetime":1767358800,"value":525},{"datetime":1767353400,"value":666},{"datetime":1767348000,"value":374}],"average_response_time":"485.939","responsetime_length":295},{"id":801799170,"friendly_name":"Telegram","url":"https://telegram.org","type":1,"sub_type":"","keyword_type":0,"keyword_case_type":0,"keyword_value":"","port":"","interval":300,"timeout":30,"status":2,"create_datetime":1763232292,"logs":[],"userId":3161943,"custom_uptime_ratio":"100.000","custom_down_durations":"0","response_times":[{"datetime":1767480480,"value":276},{"datetime":1767478320,"value":264},{"datetime":1767475200,"value":276},{"datetime":1767472800,"value":271},{"datetime":1767470400,"value":261},{"datetime":1767468000,"value":268},{"datetime":1767465600,"value":285},{"datetime":1767463200,"value":261},{"datetime":1767460800,"value":292},{"datetime":1767458400,"value":273},{"datetime":1767456000,"value":276},{"datetime":1767453300,"value":277},{"datetime":1767450900,"value":283},{"datetime":1767448500,"value":268},{"datetime":1767446100,"value":280},{"datetime":1767443700,"value":281},{"datetime":1767441300,"value":270},{"datetime":1767438900,"value":265},{"datetime":1767436500,"value":267},{"datetime":1767434100,"value":277},{"datetime":1767431700,"value":265},{"datetime":1767429300,"value":281},{"datetime":1767426900,"value":266},{"datetime":1767424500,"value":277},{"datetime":1767421800,"value":279},{"datetime":1767419400,"value":272},{"datetime":1767417000,"value":266},{"datetime":1767414600,"value":281},{"datetime":1767412200,"value":264},{"datetime":1767409800,"value":276},{"datetime":1767407400,"value":282},{"datetime":1767404700,"value":269},{"datetime":1767402300,"value":264},{"datetime":1767399900,"value":277},{"datetime":1767397500,"value":277},{"datetime":1767395100,"value":294},{"datetime":1767369600,"value":275},{"datetime":1767364200,"value":286},{"datetime":1767358800,"value":271},{"datetime":1767353400,"value":279},{"datetime":1767348000,"value":270}],"average_response_time":"275.892","responsetime_length":295},{"id":801799172,"friendly_name":"Twitch","url":"https://twitch.tv","type":1,"sub_type":"","keyword_type":0,"keyword_case_type":0,"keyword_value":"","port":"","interval":300,"timeout":30,"status":9,"create_datetime":1763232301,"logs":[{"type":1,"datetime":1767480753,"duration":0,"reason":{"code":"405","detail":"Method Not Allowed"}},{"type":2,"datetime":1767480399,"duration":354,"reason":{"code":"200","detail":"OK"}},{"type":1,"datetime":1767478570,"duration":1829,"reason":{"code":"405","detail":"Method Not Allowed"}},{"type":2,"datetime":1767475594,"duration":2976,"reason":{"code":"200","detail":"OK"}},{"type":1,"datetime":1767473154,"duration":2440,"reason":{"code":"405","detail":"Method Not Allowed"}},{"type":2,"datetime":1767472796,"duration":358,"reason":{"code":"200","detail":"OK"}},{"type":1,"datetime":1767471882,"duration":914,"reason":{"code":"405","detail":"Method Not Allowed"}},{"type":2,"datetime":1767470198,"duration":1684,"reason":{"code":"200","detail":"OK"}},{"type":1,"datetime":1767469893,"duration":305,"reason":{"code":"405","detail":"Method Not Allowed"}},{"type":2,"datetime":1767467685,"duration":2208,"reason":{"code":"200","detail":"OK"}},{"type":1,"datetime":1767467380,"duration":305,"reason":{"code":"405","detail":"Method Not Allowed"}},{"type":2,"datetime":1767465141,"duration":2239,"reason":{"code":"200","detail":"OK"}},{"type":1,"datetime":1767464525,"duration":616,"reason":{"code":"405","detail":"Method Not Allowed"}},{"type":2,"datetime":1767462846,"duration":1679,"reason":{"code":"200","detail":"OK"}},{"type":1,"datetime":1767462237,"duration":609,"reason":{"code":"405","detail":"Method Not Allowed"}},{"type":2,"datetime":1767460566,"duration":1671,"reason":{"code":"200","detail":"OK"}},{"type":1,"datetime":1767459953,"duration":613,"reason":{"code":"405","detail":"Method Not Allowed"}},{"type":2,"datetime":1767458955,"duration":998,"reason":{"code":"200","detail":"OK"}},{"type":1,"datetime":1767457422,"duration":1533,"reason":{"code":"405","detail":"Method Not Allowed"}},{"type":2,"datetime":1767454849,"duration":2573,"reason":{"code":"200","detail":"OK"}},{"type":1,"datetime":1767454239,"duration":610,"reason":{"code":"405","detail":"Method Not Allowed"}},{"type":2,"datetime":1767420438,"duration":33801,"reason":{"code":"200","detail":"OK"}},{"type":1,"datetime":1767420133,"duration":305,"reason":{"code":"405","detail":"Method Not Allowed"}},{"type":2,"datetime":1767418831,"duration":1302,"reason":{"code":"200","detail":"OK"}},{"type":1,"datetime":1767418526,"duration":305,"reason":{"code":"405","detail":"Method Not Allowed"}},{"type":2,"datetime":1767413871,"duration":4655,"reason":{"code":"200","detail":"OK"}},{"type":1,"datetime":1767413262,"duration":609,"reason":{"code":"405","detail":"Method Not Allowed"}},{"type":2,"datetime":1767410314,"duration":2948,"reason":{"code":"200","detail":"OK"}},{"type":1,"datetime":1767408785,"duration":1529,"reason":{"code":"405","detail":"Method Not Allowed"}},{"type":2,"datetime":1767407718,"duration":1067,"reason":{"code":"200","detail":"OK"}},{"type":1,"datetime":1767407109,"duration":609,"reason":{"code":"405","detail":"Method Not Allowed"}},{"type":2,"datetime":1767406755,"duration":354,"reason":{"code":"200","detail":"OK"}},{"type":1,"datetime":1767406450,"duration":305,"reason":{"code":"405","detail":"Method Not Allowed"}},{"type":2,"datetime":1767405481,"duration":969,"reason":{"code":"200","detail":"OK"}},{"type":1,"datetime":1767405177,"duration":304,"reason":{"code":"405","detail":"Method Not Allowed"}},{"type":2,"datetime":1767404491,"duration":686,"reason":{"code":"200","detail":"OK"}},{"type":1,"datetime":1767402355,"duration":2136,"reason":{"code":"405","detail":"Method Not Allowed"}},{"type":2,"datetime":1767400420,"duration":1935,"reason":{"code":"200","detail":"OK"}},{"type":1,"datetime":1767399812,"duration":608,"reason":{"code":"405","detail":"Method Not Allowed"}},{"type":2,"datetime":1767398767,"duration":1045,"reason":{"code":"200","detail":"OK"}},{"type":1,"datetime":1767397547,"duration":1220,"reason":{"code":"405","detail":"Method Not Allowed"}},{"type":2,"datetime":1767395895,"duration":1652,"reason":{"code":"200","detail":"OK"}},{"type":1,"datetime":1767395285,"duration":610,"reason":{"code":"405","detail":"Method Not Allowed"}},{"type":2,"datetime":1767390285,"duration":5000,"reason":{"code":"200","detail":"OK"}},{"type":1,"datetime":1767389067,"duration":1218,"reason":{"code":"405","detail":"Method Not Allowed"}},{"type":2,"datetime":1767384910,"duration":4157,"reason":{"code":"200","detail":"OK"}},{"type":1,"datetime":1767384602,"duration":308,"reason":{"code":"405","detail":"Method Not Allowed"}},{"type":2,"datetime":1767383942,"duration":660,"reason":{"code":"200","detail":"OK"}},{"type":1,"datetime":1767383529,"duration":413,"reason":{"code":"405","detail":"Method Not Allowed"}},{"type":2,"datetime":1767382507,"duration":1022,"reason":{"code":"200","detail":"OK"}},{"type":1,"datetime":1767382202,"duration":305,"reason":{"code":"405","detail":"Method Not Allowed"}},{"type":2,"datetime":1767377962,"duration":4240,"reason":{"code":"200","detail":"OK"}},{"type":1,"datetime":1767377049,"duration":913,"reason":{"code":"405","detail":"Method Not Allowed"}},{"type":2,"datetime":1767375779,"duration":1270,"reason":{"code":"200","detail":"OK"}},{"type":1,"datetime":1767374556,"duration":1223,"reason":{"code":"405","detail":"Method Not Allowed"}},{"type":2,"datetime":1767368743,"duration":5813,"reason":{"code":"200","detail":"OK"}},{"type":1,"datetime":1767368435,"duration":308,"reason":{"code":"405","detail":"Method Not Allowed"}},{"type":2,"datetime":1767366103,"duration":2332,"reason":{"code":"200","detail":"OK"}},{"type":1,"datetime":1767365795,"duration":308,"reason":{"code":"405","detail":"Method Not Allowed"}},{"type":2,"datetime":1767336149,"duration":29646,"reason":{"code":"200","detail":"OK"}},{"type":1,"datetime":1767335538,"duration":611,"reason":{"code":"405","detail":"Method Not Allowed"}},{"type":2,"datetime":1767328380,"duration":7158,"reason":{"code":"200","detail":"OK"}},{"type":1,"datetime":1767326550,"duration":1830,"reason":{"code":"405","detail":"Method Not Allowed"}},{"type":2,"datetime":1767325885,"duration":665,"reason":{"code":"200","detail":"OK"}},{"type":1,"datetime":1767325276,"duration":609,"reason":{"code":"405","detail":"Method Not Allowed"}},{"type":2,"datetime":1767323017,"duration":2259,"reason":{"code":"200","detail":"OK"}},{"type":1,"datetime":1767322410,"duration":607,"reason":{"code":"405","detail":"Method Not Allowed"}},{"type":2,"datetime":1767322055,"duration":355,"reason":{"code":"200","detail":"OK"}},{"type":1,"datetime":1767321750,"duration":305,"reason":{"code":"405","detail":"Method Not Allowed"}},{"type":2,"datetime":1767321395,"duration":355,"reason":{"code":"200","detail":"OK"}},{"type":1,"datetime":1767319870,"duration":1525,"reason":{"code":"405","detail":"Method Not Allowed"}},{"type":2,"datetime":1767318830,"duration":1040,"reason":{"code":"200","detail":"OK"}},{"type":1,"datetime":1767317912,"duration":918,"reason":{"code":"405","detail":"Method Not Allowed"}},{"type":2,"datetime":1767313996,"duration":3916,"reason":{"code":"200","detail":"OK"}},{"type":1,"datetime":1767311249,"duration":2747,"reason":{"code":"405","detail":"Method Not Allowed"}},{"type":2,"datetime":1767306668,"duration":4581,"reason":{"code":"200","detail":"OK"}},{"type":1,"datetime":1767306059,"duration":609,"reason":{"code":"405","detail":"Method Not Allowed"}},{"type":2,"datetime":1767304334,"duration":1725,"reason":{"code":"200","detail":"OK"}},{"type":1,"datetime":1767304027,"duration":307,"reason":{"code":"405","detail":"Method Not Allowed"}},{"type":2,"datetime":1767302076,"duration":1951,"reason":{"code":"200","detail":"OK"}},{"type":1,"datetime":1767301770,"duration":306,"reason":{"code":"405","detail":"Method Not Allowed"}},{"type":2,"datetime":1767300443,"duration":1327,"reason":{"code":"200","detail":"OK"}},{"type":1,"datetime":1767299525,"duration":918,"reason":{"code":"405","detail":"Method Not Allowed"}},{"type":2,"datetime":1767297595,"duration":1930,"reason":{"code":"200","detail":"OK"}},{"type":1,"datetime":1767296681,"duration":914,"reason":{"code":"405","detail":"Method Not Allowed"}},{"type":2,"datetime":1767293357,"duration":3324,"reason":{"code":"200","detail":"OK"}},{"type":1,"datetime":1767292443,"duration":914,"reason":{"code":"405","detail":"Method Not Allowed"}},{"type":2,"datetime":1767289519,"duration":2924,"reason":{"code":"200","detail":"OK"}},{"type":1,"datetime":1767288911,"duration":608,"reason":{"code":"405","detail":"Method Not Allowed"}},{"type":2,"datetime":1767285936,"duration":2975,"reason":{"code":"200","detail":"OK"}},{"type":1,"datetime":1767285323,"duration":613,"reason":{"code":"405","detail":"Method Not Allowed"}},{"type":2,"datetime":1767281746,"duration":3577,"reason":{"code":"200","detail":"OK"}},{"type":1,"datetime":1767281438,"duration":308,"reason":{"code":"405","detail":"Method Not Allowed"}},{"type":2,"datetime":1767277948,"duration":3490,"reason":{"code":"200","detail":"OK"}},{"type":1,"datetime":1767277644,"duration":304,"reason":{"code":"405","detail":"Method Not Allowed"}},{"type":2,"datetime":1767273144,"duration":4500,"reason":{"code":"200","detail":"OK"}},{"type":1,"datetime":1767272839,"duration":305,"reason":{"code":"405","detail":"Method Not Allowed"}},{"type":2,"datetime":1767245776,"duration":27063,"reason":{"code":"200","detail":"OK"}},{"type":1,"datetime":1767244558,"duration":1218,"reason":{"code":"405","detail":"Method Not Allowed"}},{"type":2,"datetime":1767244203,"duration":355,"reason":{"code":"200","detail":"OK"}},{"type":1,"datetime":1767243290,"duration":913,"reason":{"code":"405","detail":"Method Not Allowed"}},{"type":2,"datetime":1767242305,"duration":985,"reason":{"code":"200","detail":"OK"}},{"type":1,"datetime":1767241082,"duration":1223,"reason":{"code":"405","detail":"Method Not Allowed"}},{"type":2,"datetime":1767240422,"duration":660,"reason":{"code":"200","detail":"OK"}},{"type":1,"datetime":1767239811,"duration":611,"reason":{"code":"405","detail":"Method Not Allowed"}},{"type":2,"datetime":1767234734,"duration":5077,"reason":{"code":"200","detail":"OK"}},{"type":1,"datetime":1767234429,"duration":305,"reason":{"code":"405","detail":"Method Not Allowed"}},{"type":2,"datetime":1767232165,"duration":2264,"reason":{"code":"200","detail":"OK"}},{"type":1,"datetime":1767231556,"duration":609,"reason":{"code":"405","detail":"Method Not Allowed"}},{"type":2,"datetime":1767229907,"duration":1649,"reason":{"code":"200","detail":"OK"}},{"type":1,"datetime":1767229602,"duration":305,"reason":{"code":"405","detail":"Method Not Allowed"}},{"type":2,"datetime":1767228942,"duration":660,"reason":{"code":"200","detail":"OK"}},{"type":1,"datetime":1767226501,"duration":2441,"reason":{"code":"405","detail":"Method Not Allowed"}},{"type":2,"datetime":1767225841,"duration":660,"reason":{"code":"200","detail":"OK"}},{"type":1,"datetime":1767225536,"duration":305,"reason":{"code":"405","detail":"Method Not Allowed"}},{"type":2,"datetime":1767224822,"duration":714,"reason":{"code":"200","detail":"OK"}},{"type":1,"datetime":1767224517,"duration":305,"reason":{"code":"405","detail":"Method Not Allowed"}},{"type":2,"datetime":1767223526,"duration":991,"reason":{"code":"200","detail":"OK"}},{"type":1,"datetime":1767221696,"duration":1830,"reason":{"code":"405","detail":"Method Not Allowed"}},{"type":2,"datetime":1767221034,"duration":662,"reason":{"code":"200","detail":"OK"}},{"type":1,"datetime":1767220119,"duration":915,"reason":{"code":"405","detail":"Method Not Allowed"}},{"type":2,"datetime":1767219766,"duration":353,"reason":{"code":"200","detail":"OK"}},{"type":1,"datetime":1767219156,"duration":610,"reason":{"code":"405","detail":"Method Not Allowed"}},{"type":2,"datetime":1767216510,"duration":2646,"reason":{"code":"200","detail":"OK"}},{"type":1,"datetime":1767215896,"duration":614,"reason":{"code":"405","detail":"Method Not Allowed"}},{"type":2,"datetime":1767205916,"duration":9980,"reason":{"code":"200","detail":"OK"}},{"type":1,"datetime":1767205001,"duration":915,"reason":{"code":"405","detail":"Method Not Allowed"}},{"type":2,"datetime":1767204647,"duration":354,"reason":{"code":"200","detail":"OK"}},{"type":1,"datetime":1767203730,"duration":917,"reason":{"code":"405","detail":"Method Not Allowed"}},{"type":2,"datetime":1767202740,"duration":990,"reason":{"code":"200","detail":"OK"}},{"type":1,"datetime":1767202435,"duration":305,"reason":{"code":"405","detail":"Method Not Allowed"}},{"type":2,"datetime":1767201420,"duration":1015,"reason":{"code":"200","detail":"OK"}},{"type":1,"datetime":1767201115,"duration":305,"reason":{"code":"405","detail":"Method Not Allowed"}},{"type":2,"datetime":1767195655,"duration":5460,"reason":{"code":"200","detail":"OK"}},{"type":1,"datetime":1767195351,"duration":304,"reason":{"code":"405","detail":"Method Not Allowed"}},{"type":2,"datetime":1767191861,"duration":3490,"reason":{"code":"200","detail":"OK"}},{"type":1,"datetime":1767191557,"duration":304,"reason":{"code":"405","detail":"Method Not Allowed"}},{"type":2,"datetime":1767171008,"duration":20549,"reason":{"code":"200","detail":"OK"}},{"type":1,"datetime":1767170395,"duration":613,"reason":{"code":"405","detail":"Method Not Allowed"}},{"type":2,"datetime":1767161673,"duration":8722,"reason":{"code":"200","detail":"OK"}},{"type":1,"datetime":1767161062,"duration":611,"reason":{"code":"405","detail":"Method Not Allowed"}},{"type":2,"datetime":1767159767,"duration":1295,"reason":{"code":"200","detail":"OK"}},{"type":1,"datetime":1767159462,"duration":305,"reason":{"code":"405","detail":"Method Not Allowed"}},{"type":2,"datetime":1767156182,"duration":3280,"reason":{"code":"200","detail":"OK"}},{"type":1,"datetime":1767155878,"duration":304,"reason":{"code":"405","detail":"Method Not Allowed"}},{"type":2,"datetime":1767154865,"duration":1013,"reason":{"code":"200","detail":"OK"}},{"type":1,"datetime":1767154560,"duration":305,"reason":{"code":"405","detail":"Method Not Allowed"}},{"type":2,"datetime":1767152604,"duration":1956,"reason":{"code":"200","detail":"OK"}},{"type":1,"datetime":1767152297,"duration":307,"reason":{"code":"405","detail":"Method Not Allowed"}},{"type":2,"datetime":1767151604,"duration":693,"reason":{"code":"200","detail":"OK"}},{"type":1,"datetime":1767150382,"duration":1222,"reason":{"code":"405","detail":"Method Not Allowed"}},{"type":2,"datetime":1767148345,"duration":2037,"reason":{"code":"200","detail":"OK"}},{"type":1,"datetime":1767147736,"duration":609,"reason":{"code":"405","detail":"Method Not Allowed"}},{"type":2,"datetime":1767147379,"duration":357,"reason":{"code":"200","detail":"OK"}},{"type":1,"datetime":1767146766,"duration":613,"reason":{"code":"405","detail":"Method Not Allowed"}},{"type":2,"datetime":1767146102,"duration":664,"reason":{"code":"200","detail":"OK"}},{"type":1,"datetime":1767145799,"duration":303,"reason":{"code":"405","detail":"Method Not Allowed"}},{"type":2,"datetime":1767143541,"duration":2258,"reason":{"code":"200","detail":"OK"}},{"type":1,"datetime":1767142922,"duration":619,"reason":{"code":"405","detail":"Method Not Allowed"}},{"type":2,"datetime":1767140554,"duration":2368,"reason":{"code":"200","detail":"OK"}},{"type":1,"datetime":1767139635,"duration":919,"reason":{"code":"405","detail":"Method Not Allowed"}},{"type":2,"datetime":1767138645,"duration":990,"reason":{"code":"200","detail":"OK"}},{"type":1,"datetime":1767138336,"duration":309,"reason":{"code":"405","detail":"Method Not Allowed"}},{"type":2,"datetime":1767136396,"duration":1940,"reason":{"code":"200","detail":"OK"}},{"type":1,"datetime":1767134864,"duration":1532,"reason":{"code":"405","detail":"Method Not Allowed"}},{"type":2,"datetime":1767129684,"duration":5180,"reason":{"code":"200","detail":"OK"}},{"type":1,"datetime":1767128762,"duration":922,"reason":{"code":"405","detail":"Method Not Allowed"}},{"type":2,"datetime":1767128071,"duration":691,"reason":{"code":"200","detail":"OK"}},{"type":1,"datetime":1767125622,"duration":2449,"reason":{"code":"405","detail":"Method Not Allowed"}},{"type":2,"datetime":1767124281,"duration":1341,"reason":{"code":"200","detail":"OK"}},{"type":1,"datetime":1767123666,"duration":615,"reason":{"code":"405","detail":"Method Not Allowed"}},{"type":2,"datetime":1767122976,"duration":690,"reason":{"code":"200","detail":"OK"}},{"type":1,"datetime":1767121753,"duration":1223,"reason":{"code":"405","detail":"Method Not Allowed"}},{"type":2,"datetime":1767121058,"duration":695,"reason":{"code":"200","detail":"OK"}},{"type":1,"datetime":1767120750,"duration":308,"reason":{"code":"405","detail":"Method Not Allowed"}},{"type":2,"datetime":1767116237,"duration":4513,"reason":{"code":"200","detail":"OK"}},{"type":1,"datetime":1767115932,"duration":305,"reason":{"code":"405","detail":"Method Not Allowed"}},{"type":2,"datetime":1767114558,"duration":1374,"reason":{"code":"200","detail":"OK"}},{"type":1,"datetime":1767114254,"duration":304,"reason":{"code":"405","detail":"Method Not Allowed"}},{"type":2,"datetime":1767112259,"duration":1995,"reason":{"code":"200","detail":"OK"}},{"type":1,"datetime":1767111648,"duration":611,"reason":{"code":"405","detail":"Method Not Allowed"}},{"type":2,"datetime":1767105165,"duration":6483,"reason":{"code":"200","detail":"OK"}},{"type":1,"datetime":1767104555,"duration":610,"reason":{"code":"405","detail":"Method Not Allowed"}},{"type":2,"datetime":1767101944,"duration":2611,"reason":{"code":"200","detail":"OK"}},{"type":1,"datetime":1767101028,"duration":916,"reason":{"code":"405","detail":"Method Not Allowed"}},{"type":2,"datetime":1767076759,"duration":24269,"reason":{"code":"200","detail":"OK"}},{"type":1,"datetime":1767075838,"duration":921,"reason":{"code":"405","detail":"Method Not Allowed"}},{"type":2,"datetime":1767070641,"duration":5197,"reason":{"code":"200","detail":"OK"}},{"type":1,"datetime":1767070017,"duration":624,"reason":{"code":"405","detail":"Method Not Allowed"}},{"type":2,"datetime":1767067496,"duration":2521,"reason":{"code":"200","detail":"OK"}},{"type":1,"datetime":1767067192,"duration":304,"reason":{"code":"405","detail":"Method Not Allowed"}},{"type":2,"datetime":1767063664,"duration":3528,"reason":{"code":"200","detail":"OK"}},{"type":1,"datetime":1767062442,"duration":1222,"reason":{"code":"405","detail":"Method Not Allowed"}},{"type":2,"datetime":1767062069,"duration":373,"reason":{"code":"200","detail":"OK"}},{"type":1,"datetime":1767060832,"duration":1237,"reason":{"code":"405","detail":"Method Not Allowed"}},{"type":2,"datetime":1767058399,"duration":2433,"reason":{"code":"200","detail":"OK"}},{"type":1,"datetime":1767057790,"duration":609,"reason":{"code":"405","detail":"Method Not Allowed"}},{"type":2,"datetime":1767057325,"duration":465,"reason":{"code":"200","detail":"OK"}},{"type":1,"datetime":1767057012,"duration":313,"reason":{"code":"405","detail":"Method Not Allowed"}},{"type":2,"datetime":1767049194,"duration":7818,"reason":{"code":"200","detail":"OK"}},{"type":1,"datetime":1767048273,"duration":921,"reason":{"code":"405","detail":"Method Not Allowed"}},{"type":98,"datetime":1765957275,"duration":0,"reason":{"code":98,"detail":"Monitor started"}},{"type":99,"datetime":1765957271,"duration":4,"reason":{"code":99,"detail":"Monitor paused"}}],"userId":3161943,"custom_uptime_ratio":"0.000","custom_down_durations":"604800","response_times":[{"datetime":1767480720,"value":42},{"datetime":1767478560,"value":94},{"datetime":1767475200,"value":45},{"datetime":1767472500,"value":34},{"datetime":1767470100,"value":59},{"datetime":1767467700,"value":64},{"datetime":1767465300,"value":51},{"datetime":1767462900,"value":65},{"datetime":1767460500,"value":55},{"datetime":1767458100,"value":53},{"datetime":1767455700,"value":67},{"datetime":1767453300,"value":60},{"datetime":1767450900,"value":53},{"datetime":1767448500,"value":42},{"datetime":1767446100,"value":51},{"datetime":1767443700,"value":58},{"datetime":1767441300,"value":63},{"datetime":1767438900,"value":64},{"datetime":1767436500,"value":62},{"datetime":1767434100,"value":99},{"datetime":1767431700,"value":90},{"datetime":1767429300,"value":74},{"datetime":1767426900,"value":95},{"datetime":1767424500,"value":43},{"datetime":1767422100,"value":38},{"datetime":1767419700,"value":45},{"datetime":1767417300,"value":63},{"datetime":1767414900,"value":79},{"datetime":1767412500,"value":70},{"datetime":1767410100,"value":107},{"datetime":1767407700,"value":76},{"datetime":1767405300,"value":83},{"datetime":1767402900,"value":108},{"datetime":1767400500,"value":64},{"datetime":1767398100,"value":59},{"datetime":1767395700,"value":32},{"datetime":1767369600,"value":58},{"datetime":1767364200,"value":44},{"datetime":1767358800,"value":62},{"datetime":1767353400,"value":52},{"datetime":1767348000,"value":55}],"average_response_time":"63.183","responsetime_length":300},{"id":801799173,"friendly_name":"Госуслуги","url":"https://gosuslugi.ru","type":1,"sub_type":"","keyword_type":0,"keyword_case_type":0,"keyword_value":"","port":"","interval":300,"timeout":30,"status":2,"create_datetime":1763232314,"logs":[],"userId":3161943,"custom_uptime_ratio":"100.000","custom_down_durations":"0","response_times":[{"datetime":1767480540,"value":510},{"datetime":1767478380,"value":400},{"datetime":1767475200,"value":485},{"datetime":1767472800,"value":389},{"datetime":1767470400,"value":403},{"datetime":1767467700,"value":475},{"datetime":1767465300,"value":399},{"datetime":1767462900,"value":407},{"datetime":1767460500,"value":445},{"datetime":1767458100,"value":470},{"datetime":1767455700,"value":401},{"datetime":1767453300,"value":393},{"datetime":1767450900,"value":433},{"datetime":1767448500,"value":470},{"datetime":1767446100,"value":415},{"datetime":1767443700,"value":411},{"datetime":1767441300,"value":417},{"datetime":1767438900,"value":390},{"datetime":1767436500,"value":611},{"datetime":1767434100,"value":395},{"datetime":1767431700,"value":473},{"datetime":1767429300,"value":581},{"datetime":1767426900,"value":530},{"datetime":1767424500,"value":412},{"datetime":1767422100,"value":435},{"datetime":1767419700,"value":533},{"datetime":1767417300,"value":412},{"datetime":1767414900,"value":450},{"datetime":1767412500,"value":370},{"datetime":1767410100,"value":520},{"datetime":1767407700,"value":438},{"datetime":1767405000,"value":389},{"datetime":1767402600,"value":440},{"datetime":1767400200,"value":470},{"datetime":1767397500,"value":442},{"datetime":1767395100,"value":431},{"datetime":1767369600,"value":412},{"datetime":1767364200,"value":537},{"datetime":1767358800,"value":427},{"datetime":1767353400,"value":441},{"datetime":1767348000,"value":423}],"average_response_time":"448.851","responsetime_length":289},{"id":801799180,"friendly_name":"КиноПоиск","url":"https://kinopoisk.ru","type":1,"sub_type":"","keyword_type":0,"keyword_case_type":0,"keyword_value":"","port":"","interval":300,"timeout":30,"status":2,"create_datetime":1763232380,"logs":[],"userId":3161943,"custom_uptime_ratio":"100.000","custom_down_durations":"0","response_times":[{"datetime":1767480420,"value":1505},{"datetime":1767477960,"value":1526},{"datetime":1767475200,"value":1329},{"datetime":1767472500,"value":1410},{"datetime":1767470100,"value":1483},{"datetime":1767467700,"value":1610},{"datetime":1767465300,"value":1479},{"datetime":1767462900,"value":1367},{"datetime":1767460500,"value":1827},{"datetime":1767458100,"value":1577},{"datetime":1767455700,"value":1381},{"datetime":1767453300,"value":1675},{"datetime":1767450900,"value":1509},{"datetime":1767448500,"value":1422},{"datetime":1767446100,"value":1509},{"datetime":1767443700,"value":1413},{"datetime":1767441300,"value":1497},{"datetime":1767438900,"value":1494},{"datetime":1767436500,"value":1436},{"datetime":1767434100,"value":1543},{"datetime":1767431400,"value":1556},{"datetime":1767429000,"value":1742},{"datetime":1767426600,"value":1454},{"datetime":1767424200,"value":1715},{"datetime":1767421800,"value":1601},{"datetime":1767419400,"value":1566},{"datetime":1767417000,"value":1525},{"datetime":1767414600,"value":1533},{"datetime":1767412200,"value":1576},{"datetime":1767409800,"value":1368},{"datetime":1767407400,"value":1513},{"datetime":1767405000,"value":1398},{"datetime":1767402600,"value":1432},{"datetime":1767400200,"value":1420},{"datetime":1767397800,"value":1610},{"datetime":1767395400,"value":1563},{"datetime":1767369600,"value":1523},{"datetime":1767364200,"value":1523},{"datetime":1767358800,"value":1379},{"datetime":1767353400,"value":1659},{"datetime":1767348000,"value":1351}],"average_response_time":"1515.551","responsetime_length":294},{"id":801799178,"friendly_name":"Пикабу","url":"https://pikabu.ru","type":1,"sub_type":"","keyword_type":0,"keyword_case_type":0,"keyword_value":"","port":"","interval":300,"timeout":30,"status":2,"create_datetime":1763232370,"logs":[],"userId":3161943,"custom_uptime_ratio":"100.000","custom_down_durations":"0","response_times":[{"datetime":1767480540,"value":408},{"datetime":1767478380,"value":391},{"datetime":1767475200,"value":420},{"datetime":1767472800,"value":444},{"datetime":1767470400,"value":436},{"datetime":1767468000,"value":445},{"datetime":1767465300,"value":433},{"datetime":1767462900,"value":436},{"datetime":1767460500,"value":434},{"datetime":1767458100,"value":430},{"datetime":1767455700,"value":428},{"datetime":1767453300,"value":421},{"datetime":1767450900,"value":485},{"datetime":1767448500,"value":431},{"datetime":1767446100,"value":433},{"datetime":1767443700,"value":496},{"datetime":1767441300,"value":437},{"datetime":1767438900,"value":420},{"datetime":1767436500,"value":453},{"datetime":1767433800,"value":443},{"datetime":1767431400,"value":462},{"datetime":1767429000,"value":435},{"datetime":1767426600,"value":459},{"datetime":1767424200,"value":419},{"datetime":1767421800,"value":447},{"datetime":1767419400,"value":416},{"datetime":1767417000,"value":398},{"datetime":1767414600,"value":411},{"datetime":1767412200,"value":403},{"datetime":1767409800,"value":399},{"datetime":1767407400,"value":386},{"datetime":1767405000,"value":424},{"datetime":1767402600,"value":391},{"datetime":1767400200,"value":389},{"datetime":1767397800,"value":405},{"datetime":1767395400,"value":409},{"datetime":1767369600,"value":426},{"datetime":1767364200,"value":431},{"datetime":1767358800,"value":405},{"datetime":1767353400,"value":423},{"datetime":1767348000,"value":436}],"average_response_time":"462.902","responsetime_length":296},{"id":801799174,"friendly_name":"СберМегаМаркет","url":"https://sbermegamarket.ru","type":1,"sub_type":"","keyword_type":0,"keyword_case_type":0,"keyword_value":"","port":"","interval":300,"timeout":30,"status":9,"create_datetime":1763232331,"logs":[{"type":1,"datetime":1767043713,"duration":0,"reason":{"code":"403","detail":"Forbidden"}}],"userId":3161943,"custom_uptime_ratio":"0.000","custom_down_durations":"604800","response_times":[{"datetime":1767480420,"value":441},{"datetime":1767477300,"value":632},{"datetime":1767474300,"value":726},{"datetime":1767471300,"value":766},{"datetime":1767468000,"value":449},{"datetime":1767465300,"value":527},{"datetime":1767462300,"value":447},{"datetime":1767459000,"value":427},{"datetime":1767456300,"value":497},{"datetime":1767453300,"value":448},{"datetime":1767450300,"value":459},{"datetime":1767447000,"value":568},{"datetime":1767444300,"value":642},{"datetime":1767441600,"value":655},{"datetime":1767438600,"value":630},{"datetime":1767435300,"value":490},{"datetime":1767432000,"value":494},{"datetime":1767429000,"value":539},{"datetime":1767426000,"value":618},{"datetime":1767423000,"value":690},{"datetime":1767420000,"value":619},{"datetime":1767417000,"value":551},{"datetime":1767414000,"value":486},{"datetime":1767411000,"value":404},{"datetime":1767408000,"value":725},{"datetime":1767405000,"value":555},{"datetime":1767401700,"value":491},{"datetime":1767398700,"value":598}],"average_response_time":"560.420","responsetime_length":112},{"id":801799175,"friendly_name":"Хитрая Лиса API","url":"https://slyfox.su","type":1,"sub_type":"","keyword_type":0,"keyword_case_type":0,"keyword_value":"","port":"","interval":300,"timeout":30,"status":2,"create_datetime":1763232343,"logs":[{"type":98,"datetime":1765957233,"duration":0,"reason":{"code":98,"detail":"Monitor started"}},{"type":99,"datetime":1765957228,"duration":5,"reason":{"code":99,"detail":"Monitor paused"}}],"userId":3161943,"custom_uptime_ratio":"100.000","custom_down_durations":"0","response_times":[{"datetime":1767480660,"value":291},{"datetime":1767478260,"value":344},{"datetime":1767475200,"value":400},{"datetime":1767472800,"value":297},{"datetime":1767470400,"value":500},{"datetime":1767468000,"value":305},{"datetime":1767465600,"value":293},{"datetime":1767463200,"value":374},{"datetime":1767460800,"value":400},{"datetime":1767458400,"value":344},{"datetime":1767456000,"value":293},{"datetime":1767453600,"value":396},{"datetime":1767451200,"value":361},{"datetime":1767448800,"value":393},{"datetime":1767446400,"value":406},{"datetime":1767444000,"value":337},{"datetime":1767441600,"value":423},{"datetime":1767439200,"value":350},{"datetime":1767436800,"value":350},{"datetime":1767434400,"value":351},{"datetime":1767432000,"value":360},{"datetime":1767429600,"value":343},{"datetime":1767427200,"value":408},{"datetime":1767424800,"value":318},{"datetime":1767422400,"value":463},{"datetime":1767420000,"value":410},{"datetime":1767417600,"value":296},{"datetime":1767415200,"value":369},{"datetime":1767412800,"value":477},{"datetime":1767410400,"value":395},{"datetime":1767408000,"value":355},{"datetime":1767405600,"value":264},{"datetime":1767403200,"value":368},{"datetime":1767400800,"value":412},{"datetime":1767398400,"value":401},{"datetime":1767396000,"value":431},{"datetime":1767369600,"value":321},{"datetime":1767364200,"value":410},{"datetime":1767358800,"value":431},{"datetime":1767353400,"value":380},{"datetime":1767348000,"value":428}],"average_response_time":"362.855","responsetime_length":296}]}